mobileone_pytorch/__init__.py
mobileone_pytorch/_depthwise_convolution.py
mobileone_pytorch/_mobileone_block.py
mobileone_pytorch/_mobileone_block_down.py
mobileone_pytorch/_mobileone_block_up.py
mobileone_pytorch/_mobileone_component.py
mobileone_pytorch/_mobileone_getters.py
mobileone_pytorch/_mobileone_network.py
mobileone_pytorch/_pointwise_convolution.py
mobileone_pytorch/_reparametrizable_module.py
mobileone_pytorch/_reparametrize.py
mobileone_pytorch-0.1.0.dist-info/LICENSE
mobileone_pytorch-0.1.0.dist-info/METADATA
mobileone_pytorch-0.1.0.dist-info/WHEEL
mobileone_pytorch-0.1.0.dist-info/top_level.txt
mobileone_pytorch-0.1.0.dist-info/RECORD
